nameko_structlog/__init__.py
nameko_structlog/constants.py
nameko_structlog/nameko_structlog.py
nameko_structlog-0.2.2.dist-info/LICENSE
nameko_structlog-0.2.2.dist-info/METADATA
nameko_structlog-0.2.2.dist-info/WHEEL
nameko_structlog-0.2.2.dist-info/top_level.txt
nameko_structlog-0.2.2.dist-info/RECORD
