Metadata-Version: 2.1
Name: nameko-structlog
Version: 0.2.2
Summary: Nameko extension exposing a structlog dependency injector
Home-page: https://github.com/tyler46/nameko-structlog
Author: Spyros Markopoulos
Author-email: mail.doctor46@gmail.com
License: Apache License, Version 2.0
Keywords: nameko logging structlog
Platform: UNKNOWN
Classifier: Programming Language :: Python
Classifier: Intended Audience :: Developers
Classifier: Natural Language :: English
Classifier: Programming Language :: Python :: 2
Classifier: Programming Language :: Python :: 2.7
Classifier: Programming Language :: Python :: 3
Classifier: Programming Language :: Python :: 3.5
Classifier: Programming Language :: Python :: 3.6
Classifier: Topic :: Internet
Requires-Dist: nameko (>=2.5.0)
Requires-Dist: structlog (>=18.2.0)
Provides-Extra: colors
Requires-Dist: colorama (>=0.4.0) ; extra == 'colors'
Provides-Extra: dev
Requires-Dist: coverage (==4.5.1) ; extra == 'dev'
Requires-Dist: pip (==18.1) ; extra == 'dev'
Requires-Dist: bumpversion (==0.5.3) ; extra == 'dev'
Requires-Dist: flake8 (==3.5.0) ; extra == 'dev'
Requires-Dist: twine (>=1.12.1) ; extra == 'dev'
Requires-Dist: wheel (>=0.32.2) ; extra == 'dev'
